crowd.py
Crowd-3.1.0.dist-info/LICENSE
Crowd-3.1.0.dist-info/METADATA
Crowd-3.1.0.dist-info/WHEEL
Crowd-3.1.0.dist-info/top_level.txt
Crowd-3.1.0.dist-info/RECORD
